openlr_decoder/__init__.py
openlr_decoder/_openlr_decoder.cpython-311-darwin.so
openlr_decoder/py.typed
openlr_decoder-0.1.10.dist-info/METADATA
openlr_decoder-0.1.10.dist-info/WHEEL
openlr_decoder-0.1.10.dist-info/licenses/LICENSE
openlr_decoder-0.1.10.dist-info/RECORD
