Metadata-Version: 2.4
Name: openlr-decoder
Version: 0.1.10
Classifier: Development Status :: 4 - Beta
Classifier: License :: OSI Approved :: MIT License
Classifier: Operating System :: OS Independent
Classifier: Programming Language :: Rust
Classifier: Programming Language :: Python :: Implementation :: CPython
Classifier: Programming Language :: Python :: 3
Classifier: Programming Language :: Python :: 3.10
Classifier: Programming Language :: Python :: 3.11
Classifier: Programming Language :: Python :: 3.12
Classifier: Programming Language :: Python :: 3.13
Classifier: Programming Language :: Python :: 3.14
Classifier: Topic :: Scientific/Engineering :: GIS
License-File: LICENSE
Summary: Fast OpenLR location reference decoder for Python
Author-email: Replica <engineering@replicahq.com>
License: MIT
Requires-Python: >=3.10
Project-URL: Homepage, https://github.com/replicahq/openlr-decoder
Project-URL: Repository, https://github.com/replicahq/openlr-decoder
